odoo/addons/hr_timesheet_predefined_description/README.rst
odoo/addons/hr_timesheet_predefined_description/__init__.py
odoo/addons/hr_timesheet_predefined_description/__manifest__.py
odoo/addons/hr_timesheet_predefined_description/demo/hr_timesheet_predefined_description_demo.xml
odoo/addons/hr_timesheet_predefined_description/i18n/es.po
odoo/addons/hr_timesheet_predefined_description/i18n/hr_timesheet_predefined_description.pot
odoo/addons/hr_timesheet_predefined_description/i18n/it.po
odoo/addons/hr_timesheet_predefined_description/models/__init__.py
odoo/addons/hr_timesheet_predefined_description/models/account_analytic_line.py
odoo/addons/hr_timesheet_predefined_description/models/hr_timesheet_predefined_description.py
odoo/addons/hr_timesheet_predefined_description/readme/CONFIGURE.rst
odoo/addons/hr_timesheet_predefined_description/readme/CONTRIBUTORS.rst
odoo/addons/hr_timesheet_predefined_description/readme/DESCRIPTION.rst
odoo/addons/hr_timesheet_predefined_description/readme/USAGE.rst
odoo/addons/hr_timesheet_predefined_description/security/ir.model.access.csv
odoo/addons/hr_timesheet_predefined_description/security/timesheet_predefined_description_security.xml
odoo/addons/hr_timesheet_predefined_description/static/description/icon.png
odoo/addons/hr_timesheet_predefined_description/static/description/index.html
odoo/addons/hr_timesheet_predefined_description/tests/__init__.py
odoo/addons/hr_timesheet_predefined_description/tests/test_account_analytic_line.py
odoo/addons/hr_timesheet_predefined_description/views/account_analytic_line_views.xml
odoo/addons/hr_timesheet_predefined_description/views/timesheet_predefined_description_views.xml
odoo14_addon_hr_timesheet_predefined_description-14.0.1.0.1.dev6.dist-info/METADATA
odoo14_addon_hr_timesheet_predefined_description-14.0.1.0.1.dev6.dist-info/WHEEL
odoo14_addon_hr_timesheet_predefined_description-14.0.1.0.1.dev6.dist-info/top_level.txt
odoo14_addon_hr_timesheet_predefined_description-14.0.1.0.1.dev6.dist-info/RECORD
